colorlog/__init__.py
colorlog/colorlog.py
colorlog/escape_codes.py
colorlog/logging.py
colorlog/tests/conftest.py
colorlog/tests/test_colorlog.py
colorlog/tests/test_config.py
colorlog/tests/test_escape_codes.py
colorlog/tests/test_example.py
colorlog/tests/test_exports.py
colorlog/tests/test_logging.py
gr_colorlog-4.2.1.dist-info/LICENSE
gr_colorlog-4.2.1.dist-info/METADATA
gr_colorlog-4.2.1.dist-info/WHEEL
gr_colorlog-4.2.1.dist-info/top_level.txt
gr_colorlog-4.2.1.dist-info/RECORD
