Metadata-Version: 2.1
Name: gr-colorlog
Version: 4.2.1
Summary: Log formatting with colors!
Home-page: https://github.com/borntyping/python-colorlog
Author: Sam Clements
Author-email: sam@borntyping.co.uk
License: MIT License
Platform: UNKNOWN
Classifier: Development Status :: 5 - Production/Stable
Classifier: Environment :: Console
Classifier: Intended Audience :: Developers
Classifier: License :: OSI Approved :: MIT License
Classifier: Operating System :: OS Independent
Classifier: Programming Language :: Python
Classifier: Programming Language :: Python :: 2
Classifier: Programming Language :: Python :: 2.6
Classifier: Programming Language :: Python :: 2.7
Classifier: Programming Language :: Python :: 3
Classifier: Programming Language :: Python :: 3.5
Classifier: Programming Language :: Python :: 3.6
Classifier: Programming Language :: Python :: 3.7
Classifier: Programming Language :: Python :: 3.8
Classifier: Topic :: Terminals
Classifier: Topic :: Utilities
Requires-Dist: colorama ; sys_platform=="win32"
